validatedoc/__init__.py
validatedoc/validatedoc.py
validatedoc-0.0.3.dist-info/LICENSE.txt
validatedoc-0.0.3.dist-info/METADATA
validatedoc-0.0.3.dist-info/RECORD
validatedoc-0.0.3.dist-info/WHEEL
validatedoc-0.0.3.dist-info/entry_points.txt
validatedoc-0.0.3.dist-info/top_level.txt
