Metadata-Version: 2.1
Name: validatedoc
Version: 0.0.3
Summary: Do some doc string validateion
Home-page: UNKNOWN
Author: Matthew Bentley
Author-email: matthew@bentley.link
License: MIT
Platform: UNKNOWN
Requires-Python: >=3.5
